pineapple/__init__.py
pineapple/__main__.py
pineapple/pineapple.py
pineapple_cli-0.1.0.dist-info/LICENSE
pineapple_cli-0.1.0.dist-info/METADATA
pineapple_cli-0.1.0.dist-info/WHEEL
pineapple_cli-0.1.0.dist-info/entry_points.txt
pineapple_cli-0.1.0.dist-info/RECORD
