Metadata-Version: 2.1
Name: pineapple-cli
Version: 0.1.0
Summary: Generate projects in seconds with a simple CLI, configuration, and documentation.
License: MIT
Author: Adam Garza
Author-email: 168875175+hyerland@users.noreply.github.com
Requires-Python: >=3.10,<4.0
Classifier: License :: OSI Approved :: MIT License
Classifier: Programming Language :: Python :: 3
Classifier: Programming Language :: Python :: 3.10
Classifier: Programming Language :: Python :: 3.11
Classifier: Programming Language :: Python :: 3.12
Requires-Dist: typer[all] (>=0.12.3,<0.13.0)
